pymsbuild_rust/pymsbuild.py
pymsbuild_rust/__init__.py
pymsbuild_rust/targets/rust-ARM64-Cargo.props
pymsbuild_rust/targets/rust-common.targets
pymsbuild_rust/targets/rust-POSIX_x64-Cargo.props
pymsbuild_rust/targets/rust-default-POSIX_x64.props
pymsbuild_rust/targets/rust-default-x64.props
pymsbuild_rust/targets/rust-POSIX_x64.props
pymsbuild_rust/targets/rust-Win32.targets
pymsbuild_rust/targets/rust-x64.targets
pymsbuild_rust/targets/rust-Win32-Cargo.props
pymsbuild_rust/targets/rust-Win32.props
pymsbuild_rust/targets/rust-default-ARM64.props
pymsbuild_rust/targets/rust-default-Win32.props
pymsbuild_rust/targets/rust-x64-Cargo.props
pymsbuild_rust/targets/rust-x64.props
pymsbuild_rust/targets/rust-POSIX_x64.targets
pymsbuild_rust/targets/rust-ARM64.props
pymsbuild_rust/targets/rust-ARM64.targets
pymsbuild_rust-0.1.8.dist-info/METADATA
pymsbuild_rust-0.1.8.dist-info/WHEEL
pymsbuild_rust-0.1.8.dist-info/RECORD